golflaskuri/__init__.py
golflaskuri/clubs/EGS.json
golflaskuri/clubs/GG.json
golflaskuri/clubs/Hirsala.json
golflaskuri/clubs/Peuramaa.json
golflaskuri/clubs/Pickala.json
golflaskuri/clubs/Ringside.json
golflaskuri/clubs/SHG.json
golflaskuri/main.py
golflaskuri/templates/course_select.html
golflaskuri/templates/handicaps.html
golflaskuri/templates/scorecard.html
golflaskuri-0.4.1.dist-info/METADATA
golflaskuri-0.4.1.dist-info/WHEEL
golflaskuri-0.4.1.dist-info/RECORD
